requester_kit/__init__.py
requester_kit/client.py
requester_kit/py.typed
requester_kit/types.py
requester_kit-0.3.0.dist-info/METADATA
requester_kit-0.3.0.dist-info/WHEEL
requester_kit-0.3.0.dist-info/licenses/LICENSE
requester_kit-0.3.0.dist-info/RECORD
