Metadata-Version: 2.4
Name: requester-kit
Version: 0.3.0
Summary: Async HTTP connector toolkit with retries, testing helpers, and Prometheus metrics.
Project-URL: Homepage, https://github.com/evstratbg/requester-kit
Project-URL: Repository, https://github.com/evstratbg/requester-kit
Project-URL: Issues, https://github.com/evstratbg/requester-kit/issues
Author-email: Bogdan <evstrat.bg@gmail.com>
License: MIT
License-File: LICENSE
Requires-Python: >=3.9
Requires-Dist: httpx>=0.27.2
Requires-Dist: orjson>=3.10.7
Requires-Dist: pydantic>=2.9.2
Requires-Dist: tenacity>=9.0.0
Provides-Extra: metrics
Requires-Dist: prometheus-client>=0.20.0; extra == 'metrics'
Provides-Extra: testing
Requires-Dist: pytest-fixture-classes>=1.0.3; extra == 'testing'
Requires-Dist: pytest-mock>=3.14.0; extra == 'testing'
Requires-Dist: pytest>=8.3.3; extra == 'testing'
